aialgorithms/4_cspbacktrack.py
aialgorithms/4_cspbraanch.py
aialgorithms/__init__.py
aialgorithms/astar.py
aialgorithms/chatbot.py
aialgorithms/graph_search.py
aialgorithms/greedy.py
aialgorithms-0.2.0.dist-info/licenses/LICENSE
aialgorithms-0.2.0.dist-info/METADATA
aialgorithms-0.2.0.dist-info/WHEEL
aialgorithms-0.2.0.dist-info/top_level.txt
aialgorithms-0.2.0.dist-info/RECORD
