Metadata-Version: 2.4
Name: aialgorithms
Version: 0.2.0
Summary: A collection of AI algorithms including BFS, DFS, A*, CSP, and more
Home-page: https://github.com/yourusername/aialgorithms
Author: Your Name
Author-email: your.email@example.com
Classifier: Programming Language :: Python :: 3
Classifier: License :: OSI Approved :: MIT License
Classifier: Operating System :: OS Independent
Requires-Python: >=3.6
License-File: LICENSE
Dynamic: author
Dynamic: author-email
Dynamic: classifier
Dynamic: description
Dynamic: description-content-type
Dynamic: home-page
Dynamic: license-file
Dynamic: requires-python
Dynamic: summary
